Workbook

Sheet Sales Data
A1: Date | B1: Product | C1: Storage | D1: Color | E1: City | F1: Sales Channel | G1: Units Sold | H1: Unit Price (₹) | I1: Revenue (₹)
A2: 2026-01-03 | B2: iPhone 15 | C2: 128GB | D2: Black | E2: Jabalpur | F2: Online | G2: 3 | H2: 55000 | I2: =G2*H2 -> 165000
A3: 2026-01-05 | B3: iPhone 15 | C3: 128GB | D3: Blue | E3: Satna | F3: Retail | G3: 2 | H3: 55000 | I3: =G3*H3 -> 110000
A4: 2026-01-08 | B4: iPhone 15 Plus | C4: 128GB | D4: Pink | E4: Bhopal | F4: Online | G4: 2 | H4: 65000 | I4: =G4*H4 -> 130000
A5: 2026-01-10 | B5: iPhone 15 Pro | C5: 256GB | D5: Natural Titanium | E5: Indore | F5: Retail | G5: 2 | H5: 90000 | I5: =G5*H5 -> 180000
A6: 2026-01-12 | B6: iPhone 15 Pro Max | C6: 256GB | D6: Blue Titanium | E6: Jabalpur | F6: Online | G6: 1 | H6: 110000 | I6: =G6*H6 -> 110000
A7: 2026-01-15 | B7: iPhone 16 | C7: 128GB | D7: Black | E7: Satna | F7: Retail | G7: 3 | H7: 70000 | I7: =G7*H7 -> 210000
A8: 2026-01-18 | B8: iPhone 16 | C8: 128GB | D8: Pink | E8: Bhopal | F8: Online | G8: 2 | H8: 70000 | I8: =G8*H8 -> 140000
A9: 2026-01-20 | B9: iPhone 16 Plus | C9: 128GB | D9: Ultramarine | E9: Indore | F9: Retail | G9: 1 | H9: 80000 | I9: =G9*H9 -> 80000
A10: 2026-01-22 | B10: iPhone 16 Pro | C10: 128GB | D10: Desert Titanium | E10: Jabalpur | F10: Online | G10: 2 | H10: 100000 | I10: =G10*H10 -> 200000
A11: 2026-01-25 | B11: iPhone 16 Pro Max | C11: 256GB | D11: Black Titanium | E11: Satna | F11: Retail | G11: 1 | H11: 120000 | I11: =G11*H11 -> 120000
A12: 2026-01-28 | B12: iPhone 15 | C12: 256GB | D12: Green | E12: Bhopal | F12: Online | G12: 2 | H12: 65000 | I12: =G12*H12 -> 130000
A13: 2026-02-02 | B13: iPhone 15 | C13: 128GB | D13: Black | E13: Indore | F13: Retail | G13: 3 | H13: 55000 | I13: =G13*H13 -> 165000
... A41: 2026-04-25 | B41: iPhone 16 Pro Max | C41: 256GB | D41: Desert Titanium | E41: Indore | F41: Retail | G41: 1 | H41: 120000 | I41: =G41*H41 -> 120000

Sheet Dashboard
A1: Apple iPhone – AI-Assisted Sales Dashboard
A3: Key Performance Indicators
A4: Total Revenue | C4: Total Units | E4: Average Order Value | G4: Best Product
A5: =SUM('Sales Data'!I2:I41) -> 6480000 | C5: =SUM('Sales Data'!G2:G41) -> 80 | E5: =AVERAGE('Sales Data'!I2:I41) -> 162000 | G5: =INDEX(A10:A14,MATCH(MAX(B10:B14),B10:B14,0)) -> iPhone 15
A8: Product-wise Sales | E8: City-wise Revenue
A9: Product | B9: Units | C9: Revenue | E9: City | F9: Revenue
A10: iPhone 15 | B10: =SUMIF('Sales Data'!B2:B41,A10,'Sales Data'!G2:G41) -> 18 | C10: =SUMIF('Sales Data'!B2:B41,A10,'Sales Data'!I2:I41) -> 1040000 | E10: Jabalpur | F10: =SUMIF('Sales Data'!E2:E41,E10,'Sales Data'!I2:I41) -> 1540000
A11: iPhone 15 Plus | B11: =SUMIF('Sales Data'!B2:B41,A11,'Sales Data'!G2:G41) -> 11 | C11: =SUMIF('Sales Data'!B2:B41,A11,'Sales Data'!I2:I41) -> 715000 | E11: Satna | F11: =SUMIF('Sales Data'!E2:E41,E11,'Sales Data'!I2:I41) -> 1620000
A12: iPhone 15 Pro | B12: =SUMIF('Sales Data'!B2:B41,A12,'Sales Data'!G2:G41) -> 8 | C12: =SUMIF('Sales Data'!B2:B41,A12,'Sales Data'!I2:I41) -> 720000 | E12: Bhopal | F12: =SUMIF('Sales Data'!E2:E41,E12,'Sales Data'!I2:I41) -> 1675000
A13: iPhone 15 Pro Max | B13: =SUMIF('Sales Data'!B2:B41,A13,'Sales Data'!G2:G41) -> 5 | C13: =SUMIF('Sales Data'!B2:B41,A13,'Sales Data'!I2:I41) -> 565000 | E13: Indore | F13: =SUMIF('Sales Data'!E2:E41,E13,'Sales Data'!I2:I41) -> 1645000
A14: iPhone 16 | B14: =SUMIF('Sales Data'!B2:B41,A14,'Sales Data'!G2:G41) -> 14 | C14: =SUMIF('Sales Data'!B2:B41,A14,'Sales Data'!I2:I41) -> 980000
A15: iPhone 16 Plus | B15: =SUMIF('Sales Data'!B2:B41,A15,'Sales Data'!G2:G41) -> 7 | C15: =SUMIF('Sales Data'!B2:B41,A15,'Sales Data'!I2:I41) -> 560000
A16: iPhone 16 Pro | B16: =SUMIF('Sales Data'!B2:B41,A16,'Sales Data'!G2:G41) -> 10 | C16: =SUMIF('Sales Data'!B2:B41,A16,'Sales Data'!I2:I41) -> 1060000 | E16: Sales Channel
A17: iPhone 16 Pro Max | B17: =SUMIF('Sales Data'!B2:B41,A17,'Sales Data'!G2:G41) -> 7 | C17: =SUMIF('Sales Data'!B2:B41,A17,'Sales Data'!I2:I41) -> 840000 | E17: Channel | F17: Units
E18: Online | F18: =SUMIF('Sales Data'!F2:F41,E18,'Sales Data'!G2:G41) -> 38
E19: Retail | F19: =SUMIF('Sales Data'!F2:F41,E19,'Sales Data'!G2:G41) -> 42
A21: AI-Assisted Insights
A22: 1. Use Pivot Tables to identify the highest-selling iPhone model and city.
A23: 2. Focus promotions on products with high unit sales but lower revenue.
A24: 3. Compare Online vs Retail sales to identify the stronger sales channel.
A25: 4. Track monthly revenue to spot growth or decline trends.
A26: 5. Prioritize inventory for the best-performing iPhone models.

Sheet Analysis
A1: Detailed Sales Analysis
A3: Product-wise Analysis | F3: City-wise Analysis
A4: Product | B4: Units Sold | C4: Revenue (₹) | D4: Avg Revenue/Record (₹) | F4: City | G4: Units Sold | H4: Revenue (₹)
A5: iPhone 15 | B5: =SUMIF('Sales Data'!B2:B41,A5,'Sales Data'!G2:G41) -> 18 | C5: =SUMIF('Sales Data'!B2:B41,A5,'Sales Data'!I2:I41) -> 1040000 | D5: =IFERROR(C5/COUNTIF('Sales Data'!B2:B41,A5),0) -> 148571.43 | F5: Jabalpur | G5: =SUMIF('Sales Data'!E2:E41,F5,'Sales Data'!G2:G41) -> 21 | H5: =SUMIF('Sales Data'!E2:E41,F5,'Sales Data'!I2:I41) -> 1540000
A6: iPhone 15 Plus | B6: =SUMIF('Sales Data'!B2:B41,A6,'Sales Data'!G2:G41) -> 11 | C6: =SUMIF('Sales Data'!B2:B41,A6,'Sales Data'!I2:I41) -> 715000 | D6: =IFERROR(C6/COUNTIF('Sales Data'!B2:B41,A6),0) -> 143000 | F6: Satna | G6: =SUMIF('Sales Data'!E2:E41,F6,'Sales Data'!G2:G41) -> 18 | H6: =SUMIF('Sales Data'!E2:E41,F6,'Sales Data'!I2:I41) -> 1620000
A7: iPhone 15 Pro | B7: =SUMIF('Sales Data'!B2:B41,A7,'Sales Data'!G2:G41) -> 8 | C7: =SUMIF('Sales Data'!B2:B41,A7,'Sales Data'!I2:I41) -> 720000 | D7: =IFERROR(C7/COUNTIF('Sales Data'!B2:B41,A7),0) -> 144000 | F7: Bhopal | G7: =SUMIF('Sales Data'!E2:E41,F7,'Sales Data'!G2:G41) -> 17 | H7: =SUMIF('Sales Data'!E2:E41,F7,'Sales Data'!I2:I41) -> 1675000
A8: iPhone 15 Pro Max | B8: =SUMIF('Sales Data'!B2:B41,A8,'Sales Data'!G2:G41) -> 5 | C8: =SUMIF('Sales Data'!B2:B41,A8,'Sales Data'!I2:I41) -> 565000 | D8: =IFERROR(C8/COUNTIF('Sales Data'!B2:B41,A8),0) -> 141250 | F8: Indore | G8: =SUMIF('Sales Data'!E2:E41,F8,'Sales Data'!G2:G41) -> 24 | H8: =SUMIF('Sales Data'!E2:E41,F8,'Sales Data'!I2:I41) -> 1645000
A9: iPhone 16 | B9: =SUMIF('Sales Data'!B2:B41,A9,'Sales Data'!G2:G41) -> 14 | C9: =SUMIF('Sales Data'!B2:B41,A9,'Sales Data'!I2:I41) -> 980000 | D9: =IFERROR(C9/COUNTIF('Sales Data'!B2:B41,A9),0) -> 196000
A10: iPhone 16 Plus | B10: =SUMIF('Sales Data'!B2:B41,A10,'Sales Data'!G2:G41) -> 7 | C10: =SUMIF('Sales Data'!B2:B41,A10,'Sales Data'!I2:I41) -> 560000 | D10: =IFERROR(C10/COUNTIF('Sales Data'!B2:B41,A10),0) -> 140000
A11: iPhone 16 Pro | B11: =SUMIF('Sales Data'!B2:B41,A11,'Sales Data'!G2:G41) -> 10 | C11: =SUMIF('Sales Data'!B2:B41,A11,'Sales Data'!I2:I41) -> 1060000 | D11: =IFERROR(C11/COUNTIF('Sales Data'!B2:B41,A11),0) -> 212000
A12: iPhone 16 Pro Max | B12: =SUMIF('Sales Data'!B2:B41,A12,'Sales Data'!G2:G41) -> 7 | C12: =SUMIF('Sales Data'!B2:B41,A12,'Sales Data'!I2:I41) -> 840000 | D12: =IFERROR(C12/COUNTIF('Sales Data'!B2:B41,A12),0) -> 168000
A15: Sales Channel Analysis | F15: Monthly Revenue Analysis
A16: Channel | B16: Units Sold | C16: Revenue (₹) | F16: Month | G16: Revenue (₹)
A17: Online | B17: =SUMIF('Sales Data'!F2:F41,A17,'Sales Data'!G2:G41) -> 38 | C17: =SUMIF('Sales Data'!F2:F41,A17,'Sales Data'!I2:I41) -> 3215000 | F17: Jan-2026 | G17: =SUMPRODUCT((MONTH('Sales Data'!A2:A41)=1)*(YEAR('Sales Data'!A2:A41)=2026)*'Sales Data'!I2:I41) -> 1575000
A18: Retail | B18: =SUMIF('Sales Data'!F2:F41,A18,'Sales Data'!G2:G41) -> 42 | C18: =SUMIF('Sales Data'!F2:F41,A18,'Sales Data'!I2:I41) -> 3265000 | F18: Feb-2026 | G18: =SUMPRODUCT((MONTH('Sales Data'!A2:A41)=2)*(YEAR('Sales Data'!A2:A41)=2026)*'Sales Data'!I2:I41) -> 1620000
F19: Mar-2026 | G19: =SUMPRODUCT((MONTH('Sales Data'!A2:A41)=3)*(YEAR('Sales Data'!A2:A41)=2026)*'Sales Data'!I2:I41) -> 1720000
F20: Apr-2026 | G20: =SUMPRODUCT((MONTH('Sales Data'!A2:A41)=4)*(YEAR('Sales Data'!A2:A41)=2026)*'Sales Data'!I2:I41) -> 1565000

Sheet AI Insights
A1: AI-Assisted Business Insights
A3: Business Question | B3: AI-Assisted Insight | C3: Recommended Action
A4: Which product should be prioritized? | B4: Compare product revenue and units in the Analysis sheet. | C4: Keep higher-performing iPhone models in stronger inventory.
A5: Which city is strongest? | B5: Use city-wise revenue to identify the leading market. | C5: Run targeted promotions in the strongest city.
A6: Which channel performs better? | B6: Compare Online and Retail units/revenue. | C6: Allocate more promotion budget to the stronger channel.
A7: What is the sales trend? | B7: Review monthly revenue from Jan–Apr 2026. | C7: Investigate months with lower revenue and plan offers.
A8: How can sales improve? | B8: Promote popular models and use city/channel insights. | C8: Create model-specific offers and improve inventory planning.
A11: AI Tools / Excel Features Used
A12: • Excel formulas: SUM, AVERAGE, SUMIF, COUNTIF, INDEX, MATCH
A13: • Data filtering and structured sales data
A14: • Charts and KPI dashboard
A15: • AI-assisted interpretation and business recommendations
A18: Important Note
A19: AI was used to support analysis, identify patterns, generate business questions and suggest actionable insights. Final conclusions were based on the Excel sales data.

Sheet Project Guide
A1: Project: Excel – AI-Assisted Sales Dashboard
A3: Objective | B3: Analyze Apple iPhone sales using Excel formulas, summaries, charts, dashboard design and AI-assisted business insights.
A4: Dataset | B4: 40 sales records covering iPhone models, storage, color, city, sales channel, units sold, unit price and revenue.
A5: Sheets | B5: Sales Data, Dashboard, Analysis, AI Insights, Project Guide
A6: Excel Skills Used | B6: SUM, AVERAGE, SUMIF, COUNTIF, INDEX, MATCH, filtering, conditional formatting and charts.
A7: AI Assistance | B7: AI was used for KPI ideas, business questions, pattern interpretation and recommendations.
A8: How to Present | B8: Open Dashboard → explain KPIs → show product/city/channel summaries → explain AI insights.
A9: How to Present | B9: Start with Dashboard → explain KPIs → show Analysis → explain AI Insights → finish with Project Guide/Viva.
